i2dgraph/__init__.py
i2dgraph/_imports_.py
i2dgraph/async-interactive_2d_graph.js
i2dgraph/async-interactive_2d_graph.js.map
i2dgraph/i2dgraph.min.js
i2dgraph/i2dgraph.min.js.map
i2dgraph/interactive_2d_graph_smooth.py
i2dgraph/interactive_bar_chart.py
i2dgraph/interactive_graph.py
i2dgraph/metadata.json
i2dgraph/package-info.json
i2dgraph-0.0.6.dist-info/licenses/LICENSE
i2dgraph-0.0.6.dist-info/METADATA
i2dgraph-0.0.6.dist-info/WHEEL
i2dgraph-0.0.6.dist-info/top_level.txt
i2dgraph-0.0.6.dist-info/RECORD
