Metadata-Version: 2.4
Name: i2dgraph
Version: 0.0.6
Summary: simple 2d graph with dragable points
Author: Lasse Bohlen <emil.bohlen@gmail.com>
License: MIT
Classifier: Framework :: Dash
License-File: LICENSE
Dynamic: author
Dynamic: classifier
Dynamic: description
Dynamic: description-content-type
Dynamic: license
Dynamic: license-file
Dynamic: summary
